cloudteam_blobber/__init__.py
cloudteam_blobber/cloudteam_blobber.py
cloudteam_blobber-1.0.9.dist-info/METADATA
cloudteam_blobber-1.0.9.dist-info/WHEEL
cloudteam_blobber-1.0.9.dist-info/licenses/LICENSE
cloudteam_blobber-1.0.9.dist-info/RECORD
