Metadata-Version: 2.4
Name: cloudteam_blobber
Version: 1.0.9
Summary: A blobber module for cloudteam
Author-email: "CloudTeam.AI" <devops@cloudteam.ai>
License-File: LICENSE
Classifier: License :: OSI Approved :: MIT License
Classifier: Operating System :: OS Independent
Classifier: Programming Language :: Python :: 3
Requires-Python: >=3.8
